{
  "title": "The Mystery of the Zodiac Ciphers",
  "segments": [
    {
      "text": "The Zodiac Killer sent a series of cryptic letters and ciphers.",
      "keywords": "enigmatic letters"
    },
    {
      "text": "Some of the ciphers remain unsolved to this day.",
      "keywords": "vintage paper and pen"
    },
    {
      "text": "These puzzles taunted law enforcement and amateur sleuths alike.",
      "keywords": "detectives at work"
    },
    {
      "text": "Expert cryptographers have attempted to decode the messages.",
      "keywords": "historic investigation"
    },
    {
      "text": "The mystery of the ciphers adds depth to the Zodiac case.",
      "keywords": "mysterious symbols"
    },
    {
      "text": "A chilling reminder of a killer's taunts that remain unanswered.",
      "keywords": "foggy city night"
    },
    {
      "text": "Follow for cases the world never forgot.",
      "keywords": "old case files"
    }
  ],
  "description": "The Zodiac Killer's ciphers remain unsolved, challenging experts and amateurs alike. Follow for daily cold cases! 🗝️",
  "hashtags": [
    "#truecrime",
    "#zodiacciphers",
    "#unsolved",
    "#coldcase",
    "#mystery",
    "#shorts",
    "#fyp"
  ]
}